pip_preserve_requirements/__init__.py
pip_preserve_requirements/__main__.py
pip_preserve_requirements/_cache.py
pip_preserve_requirements/_compat.py
pip_preserve_requirements/_config.py
pip_preserve_requirements/_norm_reqs.py
pip_preserve_requirements/_pip_vcs_url.py
pip_preserve_requirements/_schemas.py
pip_preserve_requirements/_tag_name_factory.py
pip_preserve_requirements/_tag_requirements.py
pip_preserve_requirements/_utils.py
pip_preserve_requirements/_vcs.py
pip_preserve_requirements/_vcs_git.py
pip_preserve_requirements/_vcs_registry.py
pip_preserve_requirements-0.3.0.dist-info/METADATA
pip_preserve_requirements-0.3.0.dist-info/WHEEL
pip_preserve_requirements-0.3.0.dist-info/entry_points.txt
pip_preserve_requirements-0.3.0.dist-info/licenses/LICENSE.txt
pip_preserve_requirements-0.3.0.dist-info/RECORD
