Metadata-Version: 2.1
Name: pip-preserve-requirements
Version: 0.3.0
Summary: Preserve pinned PIP requirements in repositories you control..
Project-URL: Documentation, https://github.com/sbidoul/pip-preserve-requirements#readme
Project-URL: Issues, https://github.com/sbidoul/pip-preserve-requirements/issues
Project-URL: Source, https://github.com/sbidoul/pip-preserve-requirements
Author-email: Stéphane Bidoul <stephane.bidoul@gmail.com>
License-Expression: MIT
License-File: LICENSE.txt
Classifier: Development Status :: 4 - Beta
Classifier: Programming Language :: Python
Classifier: Programming Language :: Python :: 3.7
Classifier: Programming Language :: Python :: 3.8
Classifier: Programming Language :: Python :: 3.9
Classifier: Programming Language :: Python :: 3.10
Classifier: Programming Language :: Python :: 3.11
Classifier: Programming Language :: Python :: Implementation :: CPython
Classifier: Programming Language :: Python :: Implementation :: PyPy
Requires-Python: >=3.7
Requires-Dist: pip-requirements-parser
Requires-Dist: pydantic
Requires-Dist: tomli; python_version < '3.11'
Requires-Dist: typer
Provides-Extra: test
Requires-Dist: coverage; extra == 'test'
Requires-Dist: mypy; extra == 'test'
Requires-Dist: pytest; extra == 'test'
